LICENSE
MANIFEST.in
README.md
requirements.txt
setup.cfg
setup.py
openvoiceplus/__init__.py
openvoiceplus/api.py
openvoiceplus/attentions.py
openvoiceplus/commons.py
openvoiceplus/hf_downloads.py
openvoiceplus/mel_processing.py
openvoiceplus/models.py
openvoiceplus/modules.py
openvoiceplus/openvoice_app.py
openvoiceplus/se_extractor.py
openvoiceplus/transforms.py
openvoiceplus/utils.py
openvoiceplus.egg-info/PKG-INFO
openvoiceplus.egg-info/SOURCES.txt
openvoiceplus.egg-info/dependency_links.txt
openvoiceplus.egg-info/requires.txt
openvoiceplus.egg-info/top_level.txt
openvoiceplus/text/__init__.py
openvoiceplus/text/cleaners.py
openvoiceplus/text/english.py
openvoiceplus/text/mandarin.py
openvoiceplus/text/symbols.py