Metadata-Version: 2.1
Name: openvoiceplus
Version: 0.0.2
Summary: OpenVoicePlus: Advanced python library for OpenVoicePlus
Home-page: https://github.com/kadirnar/OpenVoicePlus
Author: kadirnar
Author-email: kadir.nar@hotmail.com
License: MIT
License-File: LICENSE
Requires-Dist: librosa==0.9.1
Requires-Dist: faster-whisper==0.9.0
Requires-Dist: pydub==0.25.1
Requires-Dist: wavmark==0.0.3
Requires-Dist: numpy==1.26.4
Requires-Dist: eng_to_ipa==0.0.2
Requires-Dist: inflect==7.0.0
Requires-Dist: unidecode==1.3.7
Requires-Dist: whisper-timestamped==1.14.2
Requires-Dist: openai
Requires-Dist: python-dotenv
Requires-Dist: pypinyin==0.50.0
Requires-Dist: cn2an==0.5.22
Requires-Dist: jieba==0.42.1
Requires-Dist: gradio==3.48.0
Requires-Dist: langid==1.1.6
